geobricks_deployment
