Metadata-Version: 1.0
Name: GeobricksDeployment
Version: 0.0.14
Summary: Geobricks Deployment.
Home-page: http://pypi.python.org/pypi/GeobricksDeployment/
Author: Simone Murzilli; Guido Barbaglia
Author-email: geobrickspy@gmail.com
License: LICENSE.txt
Platform: UNKNOWN
